pkg/__init__.py
pkg/colleges.py
pkg/school_districts.py
pkg/schools.py
pkg/utils.py
us_school_data_api-0.0.1.dist-info/LICENSE
us_school_data_api-0.0.1.dist-info/METADATA
us_school_data_api-0.0.1.dist-info/WHEEL
us_school_data_api-0.0.1.dist-info/top_level.txt
us_school_data_api-0.0.1.dist-info/RECORD
